KratosMultiphysics/DemStructuresCouplingApplication/__init__.py
KratosMultiphysics/DemStructuresCouplingApplication/control_module_fem_dem_utility.py
KratosMultiphysics/DemStructuresCouplingApplication/control_module_process.py
KratosMultiphysics/DemStructuresCouplingApplication/dem_fem_coupling_algorithm.py
KratosMultiphysics/DemStructuresCouplingApplication/dem_fem_launcher.py
KratosMultiphysics/DemStructuresCouplingApplication/dem_main_script_ready_for_coupling_with_fem.py
KratosMultiphysics/DemStructuresCouplingApplication/dem_poromechanics_coupling_analysis_stage.py
KratosMultiphysics/DemStructuresCouplingApplication/dem_structures_coupling_gid_output.py
KratosMultiphysics/DemStructuresCouplingApplication/multiaxial_control_module_fem_dem_generalized_2d_utility.py
KratosMultiphysics/DemStructuresCouplingApplication/sand_production_post_process_tool.py
KratosMultiphysics/DemStructuresCouplingApplication/sp_dem_fem_coupling_algorithm.py
KratosMultiphysics/DemStructuresCouplingApplication/sp_dem_fem_launcher.py
KratosMultiphysics/DemStructuresCouplingApplication/sp_statistics.py
KratosMultiphysics/DemStructuresCouplingApplication/sp_statistics_2.py
KratosMultiphysics/DemStructuresCouplingApplication/stress_failure_check_utility.py
KratosMultiphysics/.libs/KratosDemStructuresCouplingApplication.cpython-310-x86_64-linux-gnu.so
KratosMultiphysics/.libs/libKratosDemStructuresCouplingCore.so
kratosdemstructurescouplingapplication-10.4.0.dist-info/METADATA
kratosdemstructurescouplingapplication-10.4.0.dist-info/WHEEL
kratosdemstructurescouplingapplication-10.4.0.dist-info/RECORD
